{
  "x-ms-vss-request-method": "GET",
  "x-ms-vss-request-url": "https://fabrikam:8080/tfs/_apis/ExtensionManagement/InstalledExtensionsByName/ms-samples/samples-contributions-guide",
  "parameters": {
    "body": null,
    "accept": "application/json; api-version=4.0-preview.1",
    "collection": "fabrikam",
    "extensionName": "samples-contributions-guide",
    "publisherName": "ms"
  },
  "responses": {
    "200": {
      "headers": {},
      "body": {
        "extensionId": "samples-contributions-guide",
        "extensionName": "Contributions Guide",
        "publisherId": "ms-samples",
        "publisherName": "Microsoft",
        "version": "0.1.35",
        "manifestVersion": 1.0,
        "baseUri": "https://ms-samples.gallerycdn.vsassets.io/extensions/ms-samples/samples-contributions-guide/0.1.35/1484832479380",
        "fallbackBaseUri": "https://ms-samples.gallery.vsassets.io/_apis/public/gallery/publisher/ms-samples/extension/samples-contributions-guide/0.1.35/assetbyname",
        "scopes": [],
        "installState": {
          "flags": "none",
          "lastUpdated": "2017-11-30T21:38:02.463Z"
        },
        "contributionTypes": [],
        "lastPublished": "2017-01-19T13:28:00.85Z",
        "files": []
      }
    }
  },
  "x-ms-vss-generated": true,
  "x-ms-vss-generated-date": "2017-11-30T16:38:04.5729875-05:00",
  "x-ms-vss-format": 1,
  "x-ms-vss-area": "ExtensionManagement",
  "x-ms-vss-resource": "InstalledExtensionsByName"
}