{
  "x-ms-vss-request-method": "GET",
  "x-ms-vss-request-url": "https://dev.azure.com/fabrikam/e5e9e01e-801a-47eb-80bb-0ad24f448abe/_apis/wiki/wikis/ffa4628c-8f6d-45c0-b61b-52c16d06c925/pages?path=%2FSamplePage973&includeContent=True",
  "parameters": {
    "path": "/SamplePage973",
    "includeContent": "True",
    "api-version": "5.1-preview.1",
    "account": "fabrikam"
  },
  "responses": {
    "200": {
      "headers": {
        "eTag": "\"4c6adda4736aae086c7ae1956da1d91aba09d6fb\""
      },
      "body": {
        "path": "/SamplePage973",
        "order": 1,
        "gitItemPath": "/SamplePage973.md",
        "subPages": [],
        "url": "https://dev.azure.com/fabrikam/e5e9e01e-801a-47eb-80bb-0ad24f448abe/_apis/wiki/wikis/ffa4628c-8f6d-45c0-b61b-52c16d06c925/pages/%2FSamplePage973",
        "remoteUrl": "https://dev.azure.com/fabrikam/e5e9e01e-801a-47eb-80bb-0ad24f448abe/_wiki/wikis/ffa4628c-8f6d-45c0-b61b-52c16d06c925?pagePath=%2FSamplePage973",
        "id": 51,
        "content": "Wiki page content"
      }
    }
  },
  "x-ms-vss-generated": true,
  "x-ms-vss-generated-date": "2019-01-08T14:09:55.4373443+05:30",
  "x-ms-vss-format": 1,
  "x-ms-vss-area": "wiki",
  "x-ms-vss-resource": "pages"
}