{
   "x-ms-vss-request-method": "PUT",
   "x-ms-vss-request-url": "https://dev.azure.com/fabrikam/_apis/work/processes/0e3d68ff-fb7f-4736-b2ce-4d677b5559bc/workItemTypes/ScrumInherited.Bug/rules/238ea945-a184-47f1-b458-9f858e9e552f?api-version=5.0-preview.2",
   "parameters": {
      "body": {
         "id": "238ea945-a184-47f1-b458-9f858e9e552f",
         "name": "myRule",
         "conditions": [{
               "conditionType": "$when",
               "field": "Microsoft.VSTS.Common.Priority",
               "value": "1"
            },
            {
               "conditionType": "$when",
               "field": "System.State",
               "value": "Active"
            }
         ],
         "actions": [{
            "actionType": "$copyValue",
            "targetField": "Microsoft.VSTS.Common.Severity",
            "value": "1 - Critical"
         }],
         "isDisabled": true
      },
      "accept": "application/json; api-version=5.0-preview.2",
      "organization": "fabrikam"
   },
   "responses": {
      "200": {
         "headers": {

         },
         "body": {
            "id": "238ea945-a184-47f1-b458-9f858e9e552f",
            "name": "myRule",
            "conditions": [{
                  "conditionType": "$when",
                  "field": "Microsoft.VSTS.Common.Priority",
                  "value": "1"
               },
               {
                  "conditionType": "$when",
                  "field": "System.State",
                  "value": "Active"
               }
            ],
            "actions": [{
               "actionType": "$copyValue",
               "targetField": "Microsoft.VSTS.Common.Severity",
               "value": "1 - Critical"
            }],
            "isDisabled": true,
            "customizationType": "custom",
            "url": "https://dev.azure.com/fabrikam/_apis/work/processes/0e3d68ff-fb7f-4736-b2ce-4d677b5559bc/workItemTypes/ScrumInherited.Bug/rules/238ea945-a184-47f1-b458-9f858e9e552f"
         }
      }
   },
   "x-ms-vss-generated": true,
   "x-ms-vss-generated-date": "2017-10-10T09:49:12.3560981-07:00",
   "x-ms-vss-format": 1,
   "x-ms-vss-area": "WorkItemTracking",
   "x-ms-vss-resource": "rules"
}