{
  "parameters": {
    "templateId": "myCustomTemplate",
    "body": {
      "name": "My Custom Template",
      "description": "A custom template for a custom process",
      "template": {
        "build": [
          {
            "enabled": true,
            "continueOnError": false,
            "alwaysRun": false,
            "displayName": "Build solution **\\*.sln",
            "task": {
              "id": "71a9a2d3-a98a-4caa-96ab-affca411ecda",
              "versionSpec": "*"
            },
            "inputs": {
              "solution": "**\\*.sln",
              "msbuildArgs": "",
              "platform": "$(platform)",
              "configuration": "$(config)",
              "clean": "false",
              "restoreNugetPackages": "true",
              "vsLocationMethod": "version",
              "vsVersion": "latest",
              "vsLocation": "",
              "msbuildLocationMethod": "version",
              "msbuildVersion": "latest",
              "msbuildArchitecture": "x86",
              "msbuildLocation": "",
              "logProjectEvents": "true"
            }
          },
          {
            "enabled": true,
            "continueOnError": false,
            "alwaysRun": false,
            "displayName": "Test Assemblies **\\*test*.dll;-:**\\obj\\**",
            "task": {
              "id": "ef087383-ee5e-42c7-9a53-ab56c98420f9",
              "versionSpec": "*"
            },
            "inputs": {
              "testAssembly": "**\\*test*.dll;-:**\\obj\\**",
              "testFiltercriteria": "",
              "runSettingsFile": "",
              "codeCoverageEnabled": "true",
              "otherConsoleOptions": "",
              "vsTestVersion": "14.0",
              "pathtoCustomTestAdapters": ""
            }
          }
        ],
        "buildNumberFormat": "$(date:yyyyMMdd)$(rev:.r)",
        "jobAuthorizationScope": "projectCollection",
        "triggers": [
          {
            "batchChanges": false,
            "branchFilters": "",
            "triggerType": "continuousIntegration"
          }
        ],
        "variables": {
          "forceClean": {
            "value": "false",
            "allowOverride": true
          },
          "config": {
            "value": "debug, release",
            "allowOverride": true
          },
          "platform": {
            "value": "any cpu",
            "allowOverride": true
          }
        }
      }
    }
  },
  "responses": {
    "200": {
      "body": {
        "id": "myCustomTemplate",
        "name": "My Custom Template",
        "canDelete": true,
        "category": "Custom",
        "description": "A custom template for a custom process",
        "template": {
          "build": [
            {
              "enabled": true,
              "continueOnError": false,
              "alwaysRun": false,
              "displayName": "Build solution **\\*.sln",
              "task": {
                "id": "71a9a2d3-a98a-4caa-96ab-affca411ecda",
                "versionSpec": "*"
              },
              "inputs": {
                "solution": "**\\*.sln",
                "msbuildArgs": "",
                "platform": "$(platform)",
                "configuration": "$(config)",
                "clean": "false",
                "restoreNugetPackages": "true",
                "vsLocationMethod": "version",
                "vsVersion": "latest",
                "vsLocation": "",
                "msbuildLocationMethod": "version",
                "msbuildVersion": "latest",
                "msbuildArchitecture": "x86",
                "msbuildLocation": "",
                "logProjectEvents": "true"
              }
            },
            {
              "enabled": true,
              "continueOnError": false,
              "alwaysRun": false,
              "displayName": "Test Assemblies **\\*test*.dll;-:**\\obj\\**",
              "task": {
                "id": "ef087383-ee5e-42c7-9a53-ab56c98420f9",
                "versionSpec": "*"
              },
              "inputs": {
                "testAssembly": "**\\*test*.dll;-:**\\obj\\**",
                "testFiltercriteria": "",
                "runSettingsFile": "",
                "codeCoverageEnabled": "true",
                "otherConsoleOptions": "",
                "vsTestVersion": "14.0",
                "pathtoCustomTestAdapters": ""
              }
            }
          ],
          "triggers": [
            {
              "branchFilters": [],
              "batchChanges": false,
              "triggerType": "continuousIntegration"
            }
          ],
          "variables": {
            "forceClean": {
              "value": "false",
              "allowOverride": true
            },
            "config": {
              "value": "debug, release",
              "allowOverride": true
            },
            "platform": {
              "value": "any cpu",
              "allowOverride": true
            }
          },
          "properties": {},
          "_links": {},
          "buildNumberFormat": "$(date:yyyyMMdd)$(rev:.r)",
          "jobAuthorizationScope": "projectCollection",
          "type": "build"
        }
      }
    }
  },
  "x-ms-vss-migrated": true
}