{
  "x-ms-vss-request-method": "PUT",
  "x-ms-vss-request-url": "https://dev.azure.com/fabrikamm0652/Test Project/Test Project Team/_apis/wit/templates/05132b3a-41d6-430f-8738-42b20b34a601",
  "parameters": {
    "body": {
      "fields": {
        "System.State": "Replaced"
      },
      "name": "New Test Template",
      "description": "Replacing template",
      "workItemTypeName": "Feature",
      "url": null
    },
    "api-version": "5.0-preview.1",
    "account": "fabrikam"
  },
  "responses": {
    "200": {
      "headers": {},
      "body": {
        "fields": {
          "System.State": "Replaced"
        },
        "id": "05132b3a-41d6-430f-8738-42b20b34a601",
        "name": "New Test Template",
        "description": "Replacing template",
        "workItemTypeName": "Feature",
        "_links": {
          "workItemType": {
            "href": "https://dev.azure.com/fabrikamm0652/00487116-45c8-4be1-a19b-ae0de259e618/_apis/wit/workItemTypes/Feature"
          },
          "self": {
            "href": "https://dev.azure.com/fabrikamm0652/Test%20Project/3481fbc6-b38e-4a68-ae98-53720872d5db/_apis/wit/templates/05132b3a-41d6-430f-8738-42b20b34a601"
          }
        },
        "url": "https://dev.azure.com/fabrikamm0652/Test%20Project/3481fbc6-b38e-4a68-ae98-53720872d5db/_apis/wit/templates/05132b3a-41d6-430f-8738-42b20b34a601"
      }
    }
  },
  "x-ms-vss-generated": true,
  "x-ms-vss-generated-date": "2019-02-01T13:44:17.7761863-08:00",
  "x-ms-vss-format": 1,
  "x-ms-vss-area": "wit",
  "x-ms-vss-resource": "workitemssamples"
}